pytorch_sphinx_theme.py
pytorch_sphinx_theme/__init__.py
pytorch_sphinx_theme/breadcrumbs.html
pytorch_sphinx_theme/footer.html
pytorch_sphinx_theme/layout.html
pytorch_sphinx_theme/search.html
pytorch_sphinx_theme/searchbox.html
pytorch_sphinx_theme/theme.conf
pytorch_sphinx_theme/theme_variables.jinja
pytorch_sphinx_theme/versions.html
pytorch_sphinx_theme/static/css/theme.css
pytorch_sphinx_theme/static/images/arrow-down-orange.svg
pytorch_sphinx_theme/static/images/arrow-right-with-tail.svg
pytorch_sphinx_theme/static/images/chevron-down-grey.svg
pytorch_sphinx_theme/static/images/chevron-right-orange.svg
pytorch_sphinx_theme/static/images/chevron-right-white.svg
pytorch_sphinx_theme/static/images/home-footer-background.jpg
pytorch_sphinx_theme/static/images/icon-close.svg
pytorch_sphinx_theme/static/images/icon-menu-dots-dark.svg
pytorch_sphinx_theme/static/images/logo-dark.svg
pytorch_sphinx_theme/static/images/logo-facebook-dark.svg
pytorch_sphinx_theme/static/images/logo-icon.svg
pytorch_sphinx_theme/static/images/logo-twitter-dark.svg
pytorch_sphinx_theme/static/images/logo.svg
pytorch_sphinx_theme/static/images/view-page-source-icon.svg
pytorch_sphinx_theme/static/js/modernizr.min.js
pytorch_sphinx_theme/static/js/theme.js
pytorch_sphinx_theme-0.0.19.dist-info/METADATA
pytorch_sphinx_theme-0.0.19.dist-info/RECORD
pytorch_sphinx_theme-0.0.19.dist-info/WHEEL
pytorch_sphinx_theme-0.0.19.dist-info/entry_points.txt
pytorch_sphinx_theme-0.0.19.dist-info/top_level.txt
